nsepy/__init__.py
nsepy/cli.py
nsepy/commons.py
nsepy/constants.py
nsepy/history.py
nsepy/live.py
nsepy/liveurls.py
nsepy/nselist.py
nsepy/symbols.py
nsepy/urls.py
nsepy/debt/__init__.py
nsepy/derivatives/__init__.py
nsepy/derivatives/archives.py
nse_data_reader-1.0.1.dist-info/LICENSE
nse_data_reader-1.0.1.dist-info/METADATA
nse_data_reader-1.0.1.dist-info/WHEEL
nse_data_reader-1.0.1.dist-info/entry_points.txt
nse_data_reader-1.0.1.dist-info/top_level.txt
nse_data_reader-1.0.1.dist-info/RECORD
