Metadata-Version: 2.1
Name: nse-data-reader
Version: 1.0.1
Summary: Library to read financial data of Indian market from NSE.
Home-page: https://github.com/akash-mitra/nsepy
Author: Akash
Author-email: akashmitra@gmail.com
Keywords: NIFTY,NSE,Stock Price
License-File: LICENSE
Requires-Dist: beautifulsoup4
Requires-Dist: requests
Requires-Dist: numpy
Requires-Dist: pandas
Requires-Dist: six
Requires-Dist: click
Requires-Dist: lxml
Requires-Dist: simpledbf
